hym/__init__.py
hym/DecisionTree/BasicDecisionTree.py
hym/DecisionTree/Variants.py
hym/DecisionTree/__init__.py
hym/DecisionTree/node.py
hym/DecisionTree/utils.py
hym/LinearRegression/__init__.py
hym/LogisticRegression/Biclassifier.py
hym/LogisticRegression/__init__.py
hym/LogisticRegression/utils.py
hym/NeuralNetwork/__init__.py
hym/SupportVectorMachine/__init__.py
hym20220592-0.1.5.dist-info/LICENSE
hym20220592-0.1.5.dist-info/METADATA
hym20220592-0.1.5.dist-info/WHEEL
hym20220592-0.1.5.dist-info/top_level.txt
hym20220592-0.1.5.dist-info/RECORD
